
{
  "header": {
    "reportVersion": 1,
    "event": "Allocation failed - JavaScript heap out of memory",
    "trigger": "FatalError",
    "filename": "report.20200124.190028.26508.0.001.json",
    "dumpEventTime": "2020-01-24T19:00:28Z",
    "dumpEventTimeStamp": "1579881628081",
    "processId": 26508,
    "cwd": "C:\\Users\\bartu\\dbot",
    "commandLine": [
      "C:\\Program Files\\nodejs\\node.exe",
      "index.js"
    ],
    "nodejsVersion": "v12.14.1",
    "wordSize": 64,
    "arch": "x64",
    "platform": "win32",
    "componentVersions": {
      "node": "12.14.1",
      "v8": "7.7.299.13-node.16",
      "uv": "1.33.1",
      "zlib": "1.2.11",
      "brotli": "1.0.7",
      "ares": "1.15.0",
      "modules": "72",
      "nghttp2": "1.40.0",
      "napi": "5",
      "llhttp": "2.0.1",
      "http_parser": "2.8.0",
      "openssl": "1.1.1d",
      "cldr": "35.1",
      "icu": "64.2",
      "tz": "2019c",
      "unicode": "12.1"
    },
    "release": {
      "name": "node",
      "lts": "Erbium",
      "headersUrl": "https://nodejs.org/download/release/v12.14.1/node-v12.14.1-headers.tar.gz",
      "sourceUrl": "https://nodejs.org/download/release/v12.14.1/node-v12.14.1.tar.gz",
      "libUrl": "https://nodejs.org/download/release/v12.14.1/win-x64/node.lib"
    },
    "osName": "Windows_NT",
    "osRelease": "10.0.18362",
    "osVersion": "Windows 10 Pro",
    "osMachine": "x86_64",
    "cpus": [
      {
        "model": "Intel(R) Core(TM) i7-9750H CPU @ 2.60GHz",
        "speed": 2592,
        "user": 38556515,
        "nice": 0,
        "sys": 20877906,
        "idle": 278078296,
        "irq": 7285687
      },
      {
        "model": "Intel(R) Core(TM) i7-9750H CPU @ 2.60GHz",
        "speed": 2592,
        "user": 17729156,
        "nice": 0,
        "sys": 6755468,
        "idle": 313027843,
        "irq": 1481843
      },
      {
        "model": "Intel(R) Core(TM) i7-9750H CPU @ 2.60GHz",
        "speed": 2592,
        "user": 52538796,
        "nice": 0,
        "sys": 10296343,
        "idle": 274677328,
        "irq": 542765
      },
      {
        "model": "Intel(R) Core(TM) i7-9750H CPU @ 2.60GHz",
        "speed": 2592,
        "user": 23487875,
        "nice": 0,
        "sys": 4646406,
        "idle": 309378187,
        "irq": 189968
      },
      {
        "model": "Intel(R) Core(TM) i7-9750H CPU @ 2.60GHz",
        "speed": 2592,
        "user": 38984375,
        "nice": 0,
        "sys": 8960140,
        "idle": 289567953,
        "irq": 295890
      },
      {
        "model": "Intel(R) Core(TM) i7-9750H CPU @ 2.60GHz",
        "speed": 2592,
        "user": 18927093,
        "nice": 0,
        "sys": 5067906,
        "idle": 313517468,
        "irq": 260984
      },
      {
        "model": "Intel(R) Core(TM) i7-9750H CPU @ 2.60GHz",
        "speed": 2592,
        "user": 36531937,
        "nice": 0,
        "sys": 9319437,
        "idle": 291661093,
        "irq": 282296
      },
      {
        "model": "Intel(R) Core(TM) i7-9750H CPU @ 2.60GHz",
        "speed": 2592,
        "user": 17172765,
        "nice": 0,
        "sys": 5871703,
        "idle": 314468000,
        "irq": 268234
      },
      {
        "model": "Intel(R) Core(TM) i7-9750H CPU @ 2.60GHz",
        "speed": 2592,
        "user": 32039015,
        "nice": 0,
        "sys": 7949593,
        "idle": 297523859,
        "irq": 306046
      },
      {
        "model": "Intel(R) Core(TM) i7-9750H CPU @ 2.60GHz",
        "speed": 2592,
        "user": 13204421,
        "nice": 0,
        "sys": 7230250,
        "idle": 317077796,
        "irq": 235515
      },
      {
        "model": "Intel(R) Core(TM) i7-9750H CPU @ 2.60GHz",
        "speed": 2592,
        "user": 29423015,
        "nice": 0,
        "sys": 10352031,
        "idle": 297737406,
        "irq": 465921
      },
      {
        "model": "Intel(R) Core(TM) i7-9750H CPU @ 2.60GHz",
        "speed": 2592,
        "user": 19193734,
        "nice": 0,
        "sys": 5089390,
        "idle": 313229328,
        "irq": 130640
      }
    ],
    "networkInterfaces": [
      {
        "name": "Wi-Fi",
        "internal": false,
        "mac": "38:00:25:92:85:5b",
        "address": "fe80::f4ff:2e95:1ef7:14f9",
        "netmask": "ffff:ffff:ffff:ffff::",
        "family": "IPv6",
        "scopeid": 19
      },
      {
        "name": "Wi-Fi",
        "internal": false,
        "mac": "38:00:25:92:85:5b",
        "address": "192.168.0.30",
        "netmask": "255.255.255.0",
        "family": "IPv4"
      },
      {
        "name": "Loopback Pseudo-Interface 1",
        "internal": true,
        "mac": "00:00:00:00:00:00",
        "address": "::1",
        "netmask": "ffff:ffff:ffff:ffff:ffff:ffff:ffff:ffff",
        "family": "IPv6",
        "scopeid": 0
      },
      {
        "name": "Loopback Pseudo-Interface 1",
        "internal": true,
        "mac": "00:00:00:00:00:00",
        "address": "127.0.0.1",
        "netmask": "255.0.0.0",
        "family": "IPv4"
      }
    ],
    "host": "DESKTOP-BUE53LA"
  },
  "javascriptStack": {
    "message": "No stack.",
    "stack": [
      "Unavailable."
    ]
  },
  "nativeStack": [
    {
      "pc": "0x00007ff6b4791759",
      "symbol": "std::basic_ostream<char,std::char_traits<char> >::operator<<+10873"
    },
    {
      "pc": "0x00007ff6b4795b7c",
      "symbol": "std::basic_ostream<char,std::char_traits<char> >::operator<<+28316"
    },
    {
      "pc": "0x00007ff6b4794b38",
      "symbol": "std::basic_ostream<char,std::char_traits<char> >::operator<<+24152"
    },
    {
      "pc": "0x00007ff6b488433b",
      "symbol": "v8::base::CPU::has_sse+37723"
    },
    {
      "pc": "0x00007ff6b5088c5e",
      "symbol": "v8::Isolate::ReportExternalAllocationLimitReached+94"
    },
    {
      "pc": "0x00007ff6b5070ca1",
      "symbol": "v8::SharedArrayBuffer::Externalize+833"
    },
    {
      "pc": "0x00007ff6b4f3e56c",
      "symbol": "v8::internal::Heap::EphemeronKeyWriteBarrierFromCode+1436"
    },
    {
      "pc": "0x00007ff6b4f49910",
      "symbol": "v8::internal::Heap::ProtectUnprotectedMemoryChunks+1312"
    },
    {
      "pc": "0x00007ff6b4f46444",
      "symbol": "v8::internal::Heap::PageFlagsAreConsistent+3204"
    },
    {
      "pc": "0x00007ff6b4f3bcd3",
      "symbol": "v8::internal::Heap::CollectGarbage+1283"
    },
    {
      "pc": "0x00007ff6b4f3a4a4",
      "symbol": "v8::internal::Heap::AddRetainedMap+2356"
    },
    {
      "pc": "0x00007ff6b4f5b775",
      "symbol": "v8::internal::Factory::NewFillerObject+53"
    },
    {
      "pc": "0x00007ff6b4cc7a49",
      "symbol": "v8::internal::interpreter::JumpTableTargetOffsets::iterator::operator=+4057"
    },
    {
      "pc": "0x00007ff6b54b463d",
      "symbol": "v8::internal::SetupIsolateDelegate::SetupHeap+567949"
    },
    {
      "pc": "0x000003273b818a3b",
      "symbol": ""
    }
  ],
  "javascriptHeap": {
    "totalMemory": 2152464384,
    "totalCommittedMemory": 2152464384,
    "usedMemory": 2146871496,
    "availableMemory": 48078864,
    "memoryLimit": 2197815296,
    "heapSpaces": {
      "read_only_space": {
        "memorySize": 262144,
        "committedMemory": 262144,
        "capacity": 261872,
        "used": 32296,
        "available": 229576
      },
      "new_space": {
        "memorySize": 2621440,
        "committedMemory": 2621440,
        "capacity": 1309360,
        "used": 467616,
        "available": 841744
      },
      "old_space": {
        "memorySize": 2132127744,
        "committedMemory": 2132127744,
        "capacity": 2129860456,
        "used": 2129513184,
        "available": 347272
      },
      "code_space": {
        "memorySize": 425984,
        "committedMemory": 425984,
        "capacity": 249120,
        "used": 249120,
        "available": 0
      },
      "map_space": {
        "memorySize": 790528,
        "committedMemory": 790528,
        "capacity": 430720,
        "used": 430720,
        "available": 0
      },
      "large_object_space": {
        "memorySize": 16187392,
        "committedMemory": 16187392,
        "capacity": 16175008,
        "used": 16175008,
        "available": 0
      },
      "code_large_object_space": {
        "memorySize": 49152,
        "committedMemory": 49152,
        "capacity": 3552,
        "used": 3552,
        "available": 0
      },
      "new_large_object_space": {
        "memorySize": 0,
        "committedMemory": 0,
        "capacity": 1309360,
        "used": 0,
        "available": 1309360
      }
    }
  },
  "resourceUsage": {
    "userCpuSeconds": 46.64,
    "kernelCpuSeconds": 1.156,
    "cpuConsumptionPercent": 251.558,
    "maxRss": 2249187328,
    "pageFaults": {
      "IORequired": 688948,
      "IONotRequired": 0
    },
    "fsActivity": {
      "reads": 193,
      "writes": 6
    }
  },
  "libuv": [
  ],
  "environmentVariables": {
    "ALLUSERSPROFILE": "C:\\ProgramData",
    "APPDATA": "C:\\Users\\bartu\\AppData\\Roaming",
    "CommonProgramFiles": "C:\\Program Files\\Common Files",
    "CommonProgramFiles(x86)": "C:\\Program Files (x86)\\Common Files",
    "CommonProgramW6432": "C:\\Program Files\\Common Files",
    "COMPUTERNAME": "DESKTOP-BUE53LA",
    "ComSpec": "C:\\Windows\\system32\\cmd.exe",
    "DriverData": "C:\\Windows\\System32\\Drivers\\DriverData",
    "HOMEDRIVE": "C:",
    "HOMEPATH": "\\Users\\bartu",
    "LOCALAPPDATA": "C:\\Users\\bartu\\AppData\\Local",
    "LOGONSERVER": "\\\\DESKTOP-BUE53LA",
    "NUMBER_OF_PROCESSORS": "12",
    "OneDrive": "C:\\Users\\bartu\\OneDrive",
    "OneDriveConsumer": "C:\\Users\\bartu\\OneDrive",
    "OS": "Windows_NT",
    "Path": "C:\\Program Files (x86)\\Common Files\\Oracle\\Java\\javapath;C:\\Windows\\system32;C:\\Windows;C:\\Windows\\System32\\Wbem;C:\\Windows\\System32\\WindowsPowerShell\\v1.0\\;C:\\Windows\\System32\\OpenSSH\\;C:\\Program Files\\NVIDIA Corporation\\NVIDIA NvDLISR;C:\\Program Files (x86)\\NVIDIA Corporation\\PhysX\\Common;C:\\Program Files\\Intel\\WiFi\\bin\\;C:\\Program Files\\Common Files\\Intel\\WirelessCommon\\;C:\\Program Files\\nodejs\\;C:\\Users\\bartu\\AppData\\Local\\Microsoft\\WindowsApps;C:\\Program Files\\Intel\\WiFi\\bin\\;C:\\Program Files\\Common Files\\Intel\\WirelessCommon\\;C:\\Users\\bartu\\AppData\\Local\\Programs\\Microsoft VS Code\\bin;C:\\Users\\bartu\\AppData\\Roaming\\npm",
    "PATHEXT": ".COM;.EXE;.BAT;.CMD;.VBS;.VBE;.JS;.JSE;.WSF;.WSH;.MSC;.CPL",
    "PROCESSOR_ARCHITECTURE": "AMD64",
    "PROCESSOR_IDENTIFIER": "Intel64 Family 6 Model 158 Stepping 10, GenuineIntel",
    "PROCESSOR_LEVEL": "6",
    "PROCESSOR_REVISION": "9e0a",
    "ProgramData": "C:\\ProgramData",
    "ProgramFiles": "C:\\Program Files",
    "ProgramFiles(x86)": "C:\\Program Files (x86)",
    "ProgramW6432": "C:\\Program Files",
    "PSModulePath": "C:\\Users\\bartu\\OneDrive\\Belgeler\\WindowsPowerShell\\Modules;C:\\Program Files\\WindowsPowerShell\\Modules;C:\\Windows\\system32\\WindowsPowerShell\\v1.0\\Modules",
    "PUBLIC": "C:\\Users\\Public",
    "SESSIONNAME": "Console",
    "SystemDrive": "C:",
    "SystemRoot": "C:\\Windows",
    "TEMP": "C:\\Users\\bartu\\AppData\\Local\\Temp",
    "TMP": "C:\\Users\\bartu\\AppData\\Local\\Temp",
    "USERDOMAIN": "DESKTOP-BUE53LA",
    "USERDOMAIN_ROAMINGPROFILE": "DESKTOP-BUE53LA",
    "USERNAME": "bartu",
    "USERPROFILE": "C:\\Users\\bartu",
    "windir": "C:\\Windows",
    "TERM_PROGRAM": "vscode",
    "TERM_PROGRAM_VERSION": "1.41.1",
    "LANG": "tr_TR.UTF-8",
    "COLORTERM": "truecolor"
  },
  "sharedObjects": [
    "C:\\Program Files\\nodejs\\node.exe",
    "C:\\Windows\\SYSTEM32\\ntdll.dll",
    "C:\\Windows\\System32\\KERNEL32.DLL",
    "C:\\Windows\\System32\\KERNELBASE.dll",
    "C:\\Windows\\System32\\WS2_32.dll",
    "C:\\Windows\\System32\\RPCRT4.dll",
    "C:\\Windows\\SYSTEM32\\dbghelp.dll",
    "C:\\Windows\\System32\\ADVAPI32.dll",
    "C:\\Windows\\System32\\ucrtbase.dll",
    "C:\\Windows\\System32\\msvcrt.dll",
    "C:\\Windows\\System32\\sechost.dll",
    "C:\\Windows\\System32\\USER32.dll",
    "C:\\Windows\\System32\\win32u.dll",
    "C:\\Windows\\System32\\GDI32.dll",
    "C:\\Windows\\System32\\gdi32full.dll",
    "C:\\Windows\\System32\\msvcp_win.dll",
    "C:\\Windows\\System32\\PSAPI.DLL",
    "C:\\Windows\\System32\\CRYPT32.dll",
    "C:\\Windows\\System32\\MSASN1.dll",
    "C:\\Windows\\SYSTEM32\\IPHLPAPI.DLL",
    "C:\\Windows\\System32\\bcrypt.dll",
    "C:\\Windows\\SYSTEM32\\USERENV.dll",
    "C:\\Windows\\System32\\profapi.dll",
    "C:\\Windows\\SYSTEM32\\WINMM.dll",
    "C:\\Windows\\SYSTEM32\\winmmbase.dll",
    "C:\\Windows\\System32\\cfgmgr32.dll",
    "C:\\Windows\\System32\\bcryptPrimitives.dll",
    "C:\\Windows\\System32\\IMM32.DLL",
    "C:\\Windows\\System32\\powrprof.dll",
    "C:\\Windows\\System32\\UMPDC.dll",
    "C:\\Windows\\SYSTEM32\\CRYPTBASE.DLL",
    "C:\\Windows\\system32\\uxtheme.dll",
    "C:\\Windows\\System32\\combase.dll",
    "C:\\Windows\\system32\\mswsock.dll",
    "C:\\Windows\\System32\\kernel.appcore.dll",
    "C:\\Windows\\System32\\NSI.dll",
    "C:\\Windows\\SYSTEM32\\dhcpcsvc6.DLL",
    "C:\\Windows\\SYSTEM32\\dhcpcsvc.DLL",
    "C:\\Windows\\SYSTEM32\\DNSAPI.dll",
    "C:\\Windows\\system32\\napinsp.dll",
    "C:\\Windows\\system32\\pnrpnsp.dll",
    "C:\\Windows\\System32\\winrnr.dll",
    "C:\\Windows\\system32\\NLAapi.dll",
    "C:\\Windows\\system32\\wshbth.dll",
    "C:\\Windows\\System32\\rasadhlp.dll",
    "C:\\Windows\\System32\\fwpuclnt.dll"
  ]
}